docsumm_ai/__init__.py
docsumm_ai/cli.py
docsumm_ai/core.py
docsumm_ai-0.1.0.dist-info/METADATA
docsumm_ai-0.1.0.dist-info/WHEEL
docsumm_ai-0.1.0.dist-info/entry_points.txt
docsumm_ai-0.1.0.dist-info/licenses/LICENSE
docsumm_ai-0.1.0.dist-info/RECORD
