Metadata-Version: 2.4
Name: docsumm-ai
Version: 0.1.0
Summary: Audience-aware document summarizer for PDF/DOCX/TXT — optimized for context retention, not token count.
Author: Rohit Rajdev
License: MIT
License-File: LICENSE
Keywords: AI,LLM,documents,docx,pdf,summarization
Requires-Python: >=3.9
Requires-Dist: jinja2>=3.1
Requires-Dist: pydantic>=2.6
Requires-Dist: pypdf>=4.3.0
Requires-Dist: python-docx>=1.1.2
Requires-Dist: rich>=13.7
Provides-Extra: llm
Requires-Dist: litellm>=1.45.0; extra == 'llm'
Requires-Dist: openai>=1.40.0; extra == 'llm'
Provides-Extra: local
Requires-Dist: ollama>=0.3.0; extra == 'local'
Requires-Dist: tiktoken>=0.7.0; extra == 'local'
